crypto_watcher/__init__.py
crypto_watcher/arg_parser.py
crypto_watcher/main.py
crypto_watcher/renderer.py
crypto_watcher/services/binance/__init__.py
crypto_watcher/services/binance/binance.py
crypto_watcher/services/binance/models.py
crypto_watcher/services/cryptonator/__init__.py
crypto_watcher/services/cryptonator/cryptonator.py
crypto_watcher/services/cryptonator/models.py
crypto_watcher/services/nbminer/__init__.py
crypto_watcher/services/nbminer/models.py
crypto_watcher/services/nbminer/nbminer.py
crypto_watcher/settings.py
crypto_watcher-0.1.5.dist-info/entry_points.txt
crypto_watcher-0.1.5.dist-info/WHEEL
crypto_watcher-0.1.5.dist-info/METADATA
crypto_watcher-0.1.5.dist-info/RECORD
