Metadata-Version: 2.1
Name: crypto-watcher
Version: 0.1.5
Summary: Monitoring for binance and NBMiner.
Home-page: https://github.com/s3rius/crypto_watcher
Author: Pavel Kirilin
Author-email: win10@list.ru
Requires-Python: >=3.8,<4.0
Classifier: Programming Language :: Python :: 3
Classifier: Programming Language :: Python :: 3.8
Classifier: Programming Language :: Python :: 3.9
Requires-Dist: pydantic (>=1.8.1,<2.0.0)
Requires-Dist: requests (>=2.25.1,<3.0.0)
Requires-Dist: rich (>=10.1.0,<11.0.0)
Project-URL: Repository, https://github.com/s3rius/crypto_watcher
